livyc/__init__.py
livyc/livyc.py
livyc-0.0.14.dist-info/LICENSE
livyc-0.0.14.dist-info/METADATA
livyc-0.0.14.dist-info/WHEEL
livyc-0.0.14.dist-info/top_level.txt
livyc-0.0.14.dist-info/RECORD
