Metadata-Version: 2.1
Name: livyc
Version: 0.0.14
Summary: Apache Livy Client
Home-page: https://github.com/Wittline/livyc
Author: Ramses Alexander Coraspe Valdez
Author-email: contacto@wittline.com
Classifier: Programming Language :: Python :: 3
Classifier: License :: OSI Approved :: MIT License
Classifier: Operating System :: OS Independent
Requires-Python: >=3.7
License-File: LICENSE
